midas_quant/__init__.py
midas_quant/environments/AccountSpot.py
midas_quant/environments/ActionSpot.py
midas_quant/environments/StockSpotEnv.py
midas_quant/environments/TradeEnv.py
midas_quant/environments/__init__.py
midas_quant/environments/plot.py
midas_quant/feed/IFeedPart.py
midas_quant/feed/IFeeder.py
midas_quant/feed/PandasFeeder.py
midas_quant/feed/PandasPart.py
midas_quant/feed/__init__.py
midas_quant/trader/TSMStockSpotEnv.py
midas_quant/trader/TradeStateMachine.py
midas_quant/trader/__init__.py
midas_quant-0.9.4.dist-info/LICENSE
midas_quant-0.9.4.dist-info/METADATA
midas_quant-0.9.4.dist-info/WHEEL
midas_quant-0.9.4.dist-info/RECORD
