Metadata-Version: 2.1
Name: midas-quant
Version: 0.9.4
Summary: A quantitative finance library for midas models.
Author: nockchun
Author-email: nockchun@gmail.com
Requires-Python: >=3.10,<4.0
Classifier: Programming Language :: Python :: 3
Classifier: Programming Language :: Python :: 3.10
Classifier: Programming Language :: Python :: 3.11
Requires-Dist: danbi (>=0.3.0,<0.4.0)
Requires-Dist: requests (>=2.32.3,<3.0.0)
Requires-Dist: transitions[diagrams] (>=0.9.2,<0.10.0)
